setup.py
image2leaflet/__init__.py
image2leaflet/cli.py
image2leaflet/process.py
image2leaflet/tiles.py
image2leaflet/utils.py
image2leaflet.egg-info/PKG-INFO
image2leaflet.egg-info/SOURCES.txt
image2leaflet.egg-info/dependency_links.txt
image2leaflet.egg-info/entry_points.txt
image2leaflet.egg-info/not-zip-safe
image2leaflet.egg-info/requires.txt
image2leaflet.egg-info/top_level.txt
image2leaflet/templates/index.html