Metadata-Version: 1.1
Name: image2leaflet
Version: 0.1.7
Summary: A command line tool for converting big images to Leaflet maps
Home-page: https://github.com/hyperknot/image2leaflet
Author: Zsolt Ero
Author-email: zsolt.ero@gmail.com
License: MIT
Platform: UNKNOWN
Classifier: Development Status :: 4 - Beta
Classifier: Intended Audience :: Developers
Classifier: License :: OSI Approved :: MIT License
Classifier: Natural Language :: English
Classifier: Programming Language :: Python :: 2
Classifier: Programming Language :: Python :: 2.7
Classifier: Programming Language :: Python :: 3
Classifier: Programming Language :: Python :: 3.3
Classifier: Programming Language :: Python :: 3.4
Classifier: Programming Language :: Python :: 3.5
